Metadata-Version: 2.1
Name: C3l3br1t1es-B1rth5-123142143523415
Version: 0.0.1
Summary: Mock package that allows you to find celebrity by date of birth
Home-page: https://github.com/faizmeghjee/C3l3br1t1es-B1rth5-123142143523415.git
Author: Room 18
License: MIT
Platform: UNKNOWN
License-File: LICENSE
